utilmeta/__init__.py
utilmeta/__main__.py
utilmeta/bin/__init__.py
utilmeta/bin/base.py
utilmeta/bin/constant.py
utilmeta/bin/meta.py
utilmeta/bin/utils.py
utilmeta/bin/commands/__init__.py
utilmeta/bin/commands/base.py
utilmeta/bin/commands/setup.py
utilmeta/bin/template/__init__.py
utilmeta/bin/template/full/__init__.py
utilmeta/bin/template/full/main.py
utilmeta/bin/template/full/meta.ini
utilmeta/bin/template/full/config/__init__.py
utilmeta/bin/template/full/config/conf.py
utilmeta/bin/template/full/config/env.py
utilmeta/bin/template/full/config/service.py
utilmeta/bin/template/full/domain/__init__.py
utilmeta/bin/template/full/service/__init__.py
utilmeta/bin/template/full/service/api.py
utilmeta/bin/template/lite/__init__.py
utilmeta/bin/template/lite/meta.ini
utilmeta/bin/template/lite/server.py
utilmeta/conf/__init__.py
utilmeta/conf/base.py
utilmeta/conf/deploy.py
utilmeta/conf/env.py
utilmeta/conf/http.py
utilmeta/conf/pool.py
utilmeta/conf/preference.py
utilmeta/conf/time.py
utilmeta/core/__init__.py
utilmeta/core/api/__init__.py
utilmeta/core/api/base.py
utilmeta/core/api/chain.py
utilmeta/core/api/decorator.py
utilmeta/core/api/endpoint.py
utilmeta/core/api/hook.py
utilmeta/core/api/route.py
utilmeta/core/api/plugins/__init__.py
utilmeta/core/api/plugins/base.py
utilmeta/core/api/plugins/cache.py
utilmeta/core/api/plugins/cors.py
utilmeta/core/api/plugins/rate.py
utilmeta/core/api/plugins/retry.py
utilmeta/core/api/specs/__init__.py
utilmeta/core/api/specs/base.py
utilmeta/core/api/specs/graphql.py
utilmeta/core/api/specs/openapi.py
utilmeta/core/api/specs/protobuf.py
utilmeta/core/auth/__init__.py
utilmeta/core/auth/base.py
utilmeta/core/auth/basic.py
utilmeta/core/auth/jwt.py
utilmeta/core/auth/oauth2.py
utilmeta/core/auth/properties.py
utilmeta/core/auth/signature.py
utilmeta/core/auth/plugins/__init__.py
utilmeta/core/auth/plugins/require.py
utilmeta/core/auth/session/__init__.py
utilmeta/core/auth/session/base.py
utilmeta-2.8.1.dist-info/METADATA
utilmeta-2.8.1.dist-info/WHEEL
utilmeta-2.8.1.dist-info/entry_points.txt
utilmeta-2.8.1.dist-info/licenses/LICENSE
utilmeta-2.8.1.dist-info/RECORD
