Metadata-Version: 2.1
Name: UtilMeta
Version: 2.8.1
Summary: UtilMeta - progressive meta framework for API development in Python
Project-URL: Homepage, https://utilmeta.com/py
Project-URL: Documentation, https://docs.utilmeta.com/py/en
Project-URL: Repository, https://github.com/utilmeta/utilmeta-py
Author-email: "Xulin Zhou (voidZXL)" <zxl@utilmeta.com>
License: Copyright (c) 2019-present Xulin Zhou (周煦林)
License-File: LICENSE
Keywords: API,RESTful,backend,declarative,devops,meta,orm,progressive,utype,web
Classifier: Development Status :: 4 - Beta
Classifier: Environment :: Web Environment
Classifier: Intended Audience :: Developers
Classifier: Intended Audience :: Information Technology
Classifier: Intended Audience :: System Administrators
Classifier: License :: OSI Approved :: Apache Software License
Classifier: Operating System :: OS Independent
Classifier: Programming Language :: Python
Classifier: Programming Language :: Python :: 3
Classifier: Programming Language :: Python :: 3 :: Only
Classifier: Programming Language :: Python :: 3.8
Classifier: Programming Language :: Python :: 3.9
Classifier: Programming Language :: Python :: 3.10
Classifier: Programming Language :: Python :: 3.11
Classifier: Programming Language :: Python :: 3.12
Classifier: Programming Language :: Python :: 3.13
Classifier: Topic :: Internet
Classifier: Topic :: Internet :: WWW/HTTP
Classifier: Topic :: Internet :: WWW/HTTP :: HTTP Servers
Classifier: Topic :: Software Development
Classifier: Topic :: Software Development :: Libraries
Classifier: Topic :: Software Development :: Libraries :: Application Frameworks
Classifier: Topic :: Software Development :: Libraries :: Python Modules
Classifier: Typing :: Typed
Requires-Python: >=3.8
Requires-Dist: aiosqlite>=0.20.0
Requires-Dist: databases>=0.7.0
Requires-Dist: django>=4.1.0
Requires-Dist: jwcrypto>=1.5.4
Requires-Dist: psutil>=5.8.0
Requires-Dist: user-agents>=2.2.0
Requires-Dist: utype>=0.6.8
Provides-Extra: all
Requires-Dist: flask>=2.3.0; extra == 'all'
Requires-Dist: sanic>=22.0.0; extra == 'all'
Requires-Dist: starlette>=0.27.0; extra == 'all'
Requires-Dist: tornado>=6.2; extra == 'all'
